README.md
setup.py
livebridge_slack/__init__.py
livebridge_slack/common.py
livebridge_slack/post.py
livebridge_slack/source.py
livebridge_slack/target.py
livebridge_slack.egg-info/PKG-INFO
livebridge_slack.egg-info/SOURCES.txt
livebridge_slack.egg-info/dependency_links.txt
livebridge_slack.egg-info/not-zip-safe
livebridge_slack.egg-info/requires.txt
livebridge_slack.egg-info/top_level.txt
livebridge_slack/converters/__init__.py
livebridge_slack/converters/liveblog_slack.py
livebridge_slack/converters/slack_scribblelive.py