Metadata-Version: 1.2
Name: livebridge-slack
Version: 0.6.0
Summary: Livebridge adapter for Slack.
Home-page: https://github.com/dpa-newslab/livebridge-slack
Author: dpa-infocom GmbH
Maintainer: Martin Borho
Maintainer-email: martin@borho.net
License: Apache Software License (http://www.apache.org/licenses/LICENSE-2.0)
Keywords: liveticker,slack,syndication
Platform: UNKNOWN
Classifier: Programming Language :: Python :: 3.5
Classifier: Topic :: Communications :: Chat
Classifier: Development Status :: 4 - Beta
Classifier: License :: OSI Approved :: Apache Software License
Classifier: Intended Audience :: Other Audience
Classifier: Operating System :: POSIX :: Linux
Classifier: Environment :: Console
Classifier: Environment :: Plugins
